ttach/__init__.py
ttach/__version__.py
ttach/aliases.py
ttach/base.py
ttach/functional.py
ttach/transforms.py
ttach/wrappers.py
ttach-0.0.3.dist-info/LICENSE
ttach-0.0.3.dist-info/METADATA
ttach-0.0.3.dist-info/WHEEL
ttach-0.0.3.dist-info/top_level.txt
ttach-0.0.3.dist-info/RECORD
