Metadata-Version: 2.1
Name: ttach
Version: 0.0.3
Summary: Images test time augmentation with PyTorch.
Home-page: https://github.com/qubvel/ttach
Author: Pavel Yakubovskiy
Author-email: qubvel@gmail.com
License: MIT
Platform: UNKNOWN
Classifier: License :: OSI Approved :: MIT License
Classifier: Programming Language :: Python
Classifier: Programming Language :: Python :: 3
Classifier: Programming Language :: Python :: Implementation :: CPython
Classifier: Programming Language :: Python :: Implementation :: PyPy
Requires-Python: >=3.0.0
Provides-Extra: test
